Metadata-Version: 2.1
Name: mp3-pcloud-cli
Version: 1.3
Summary: Auto-download songs from Youtube and upload them to pCloud.
Author: Sam Pomerantz
Author-email: sam@sampomerantz.me
Project-URL: Source, https://github.com/SamPom100/mp3pCloudCLI
Project-URL: Portfolio, https://sampomerantz.me
Requires-Dist: requests
Requires-Dist: yt-dlp
